README.md
setup.py
src/lstmx/__init__.py
src/lstmx.egg-info/PKG-INFO
src/lstmx.egg-info/SOURCES.txt
src/lstmx.egg-info/dependency_links.txt
src/lstmx.egg-info/top_level.txt
src/lstmx/LSTM/__init__.py
src/lstmx/LSTM/main.py
src/lstmx/LSTM/Data_preprocessing/__init__.py
src/lstmx/LSTM/Data_preprocessing/data_preprocessing.py
src/lstmx/LSTM/Model_Build/__init__.py
src/lstmx/LSTM/Model_Build/model_LSTM.py
src/lstmx/LSTM/Model_Predict/__init__.py
src/lstmx/LSTM/Model_Predict/predict.py
src/lstmx/LSTM/Model_Train/__init__.py
src/lstmx/LSTM/Model_Train/train.py